layered_config_tree/__about__.py
layered_config_tree/__init__.py
layered_config_tree/_version.py
layered_config_tree/exceptions.py
layered_config_tree/main.py
layered_config_tree/py.typed
layered_config_tree/types.py
layered_config_tree/utilities.py
layered_config_tree-4.0.7.dist-info/licenses/LICENSE.txt
layered_config_tree-4.0.7.dist-info/METADATA
layered_config_tree-4.0.7.dist-info/WHEEL
layered_config_tree-4.0.7.dist-info/top_level.txt
layered_config_tree-4.0.7.dist-info/RECORD
